setup.py
unittest_continuous/__init__.py
unittest_continuous/decorators.py
unittest_continuous.egg-info/PKG-INFO
unittest_continuous.egg-info/SOURCES.txt
unittest_continuous.egg-info/dependency_links.txt
unittest_continuous.egg-info/top_level.txt