Metadata-Version: 1.0
Name: unittest-continuous
Version: 0.1
Summary: Monkey patches the python unittest module to send results to continuous.io
Home-page: https://github.com/continuous/unittest-continuous
Author: Adam Charnock
Author-email: adam@playnice.ly
License: Apache Software License
Platform: UNKNOWN
Classifier: Development Status :: 4 - Beta
Classifier: Environment :: Plugins
Classifier: Intended Audience :: Developers
Classifier: Natural Language :: English
Classifier: Programming Language :: Python :: 2.6
Classifier: Topic :: Software Development :: Quality Assurance
Classifier: Topic :: Software Development :: Testing
